datatrack/__init__.py
datatrack/__main__.py
datatrack/artifact.py
datatrack/config.py
datatrack/dbaccess.py
datatrack/experiment.py
datatrack/run.py
datatrack/s3path.py
datatrack-0.1.7.dist-info/LICENSE
datatrack-0.1.7.dist-info/METADATA
datatrack-0.1.7.dist-info/WHEEL
datatrack-0.1.7.dist-info/entry_points.txt
datatrack-0.1.7.dist-info/top_level.txt
datatrack-0.1.7.dist-info/RECORD
