Metadata-Version: 2.2
Name: datatrack
Version: 0.1.7
Summary: Tracks your data transformations.
Author: romk
License:                     GNU GENERAL PUBLIC LICENSE
Project-URL: Homepage, https://gitlab.com/romk/datatrack
Classifier: Development Status :: 4 - Beta
Classifier: Operating System :: MacOS :: MacOS X
Classifier: Operating System :: POSIX :: Linux
Classifier: Intended Audience :: Developers
Classifier: Programming Language :: Python
Classifier: Programming Language :: Python :: 3
Classifier: License :: OSI Approved :: GNU General Public License (GPL)
Classifier: License :: OSI Approved :: GNU General Public License v3 (GPLv3)
Classifier: Topic :: Software Development
Requires-Python: >=3.9
License-File: LICENSE
Requires-Dist: psycopg[binary]
Requires-Dist: boto3[crt]
Requires-Dist: tomli; python_version < "3.11"
Requires-Dist: docopt
